poppler/__init__.py
poppler/__version__.py
poppler_utils-0.1.0.dist-info/LICENSE
poppler_utils-0.1.0.dist-info/METADATA
poppler_utils-0.1.0.dist-info/WHEEL
poppler_utils-0.1.0.dist-info/top_level.txt
poppler_utils-0.1.0.dist-info/RECORD
